{
	"posts": [{ "id": 1, "title": "json-server", "author": "typicode" }],
	"comments": [{ "id": 1, "body": "some comment", "postId": 1 }],
	"orders": [
		{
			"id": "1",
			"name": "Rudolph Robel",
			"state": "Maine",
			"createAt": "2021-05-21T16:24:06.240Z"
		},
		{
			"id": "2",
			"name": "Jeannette Collier",
			"state": "Texas",
			"createAt": "2021-05-22T08:51:02.397Z"
		},
		{
			"id": "3",
			"name": "Sadie Pacocha",
			"state": "Minnesota",
			"createAt": "2021-05-22T11:04:01.696Z"
		},
		{
			"id": "4",
			"name": "Monica Purdy",
			"state": "Texas",
			"createAt": "2021-05-21T17:38:27.047Z"
		},
		{
			"id": "5",
			"name": "Doris Gottlieb",
			"state": "Nevada",
			"createAt": "2021-05-22T02:38:16.337Z"
		},
		{
			"id": "6",
			"name": "Gary Harber PhD",
			"state": "Indiana",
			"createAt": "2021-05-22T06:21:12.867Z"
		},
		{
			"id": "7",
			"name": "Rachael Fahey MD",
			"state": "Missouri",
			"createAt": "2021-05-22T13:27:13.140Z"
		},
		{
			"id": "8",
			"name": "Salvador McCullough",
			"state": "North Dakota",
			"createAt": "2021-05-22T06:20:52.008Z"
		},
		{
			"id": "9",
			"name": "Emma Brekke",
			"state": "California",
			"createAt": "2021-05-22T07:39:33.780Z"
		},
		{
			"id": "10",
			"name": "Lance Smitham",
			"state": "New Mexico",
			"createAt": "2021-05-22T08:38:13.858Z"
		},
		{
			"id": "11",
			"name": "Elena White",
			"state": "Utah",
			"createAt": "2021-05-21T23:32:30.134Z"
		},
		{
			"id": "12",
			"name": "Lillian Kessler",
			"state": "California",
			"createAt": "2021-05-22T02:14:23.188Z"
		},
		{
			"id": "13",
			"name": "Esther Corwin",
			"state": "Rhode Island",
			"createAt": "2021-05-22T09:14:35.919Z"
		},
		{
			"id": "14",
			"name": "Mandy Kozey",
			"state": "Arkansas",
			"createAt": "2021-05-22T10:04:04.273Z"
		},
		{
			"id": "15",
			"name": "Veronica Schuppe",
			"state": "Indiana",
			"createAt": "2021-05-22T00:14:24.224Z"
		},
		{
			"id": "16",
			"name": "Elaine Pfeffer",
			"state": "Iowa",
			"createAt": "2021-05-22T05:55:23.324Z"
		},
		{
			"id": "17",
			"name": "Lamar Gislason",
			"state": "Oregon",
			"createAt": "2021-05-22T02:45:07.015Z"
		},
		{
			"id": "18",
			"name": "Louise Abernathy",
			"state": "Florida",
			"createAt": "2021-05-22T12:54:13.607Z"
		},
		{
			"id": "19",
			"name": "Mr. Bertha Skiles",
			"state": "Vermont",
			"createAt": "2021-05-21T20:08:38.389Z"
		},
		{
			"id": "20",
			"name": "Jennie Terry",
			"state": "New York",
			"createAt": "2021-05-22T14:08:30.264Z"
		}
	],
	"products": [
		{
			"id": "1",
			"name": "Rudolph Robel",
			"state": "Maine",
			"createAt": "2021-05-21T16:24:06.240Z"
		},
		{
			"id": "2",
			"name": "Jeannette Collier",
			"state": "Texas",
			"createAt": "2021-05-22T08:51:02.397Z"
		},
		{
			"id": "3",
			"name": "Sadie Pacocha",
			"state": "Minnesota",
			"createAt": "2021-05-22T11:04:01.696Z"
		},
		{
			"id": "4",
			"name": "Monica Purdy",
			"state": "Texas",
			"createAt": "2021-05-21T17:38:27.047Z"
		},
		{
			"id": "5",
			"name": "Doris Gottlieb",
			"state": "Nevada",
			"createAt": "2021-05-22T02:38:16.337Z"
		},
		{
			"id": "6",
			"name": "Gary Harber PhD",
			"state": "Indiana",
			"createAt": "2021-05-22T06:21:12.867Z"
		},
		{
			"id": "7",
			"name": "Rachael Fahey MD",
			"state": "Missouri",
			"createAt": "2021-05-22T13:27:13.140Z"
		},
		{
			"id": "8",
			"name": "Salvador McCullough",
			"state": "North Dakota",
			"createAt": "2021-05-22T06:20:52.008Z"
		},
		{
			"id": "9",
			"name": "Emma Brekke",
			"state": "California",
			"createAt": "2021-05-22T07:39:33.780Z"
		},
		{
			"id": "10",
			"name": "Lance Smitham",
			"state": "New Mexico",
			"createAt": "2021-05-22T08:38:13.858Z"
		},
		{
			"id": "11",
			"name": "Elena White",
			"state": "Utah",
			"createAt": "2021-05-21T23:32:30.134Z"
		},
		{
			"id": "12",
			"name": "Lillian Kessler",
			"state": "California",
			"createAt": "2021-05-22T02:14:23.188Z"
		},
		{
			"id": "13",
			"name": "Esther Corwin",
			"state": "Rhode Island",
			"createAt": "2021-05-22T09:14:35.919Z"
		},
		{
			"id": "14",
			"name": "Mandy Kozey",
			"state": "Arkansas",
			"createAt": "2021-05-22T10:04:04.273Z"
		},
		{
			"id": "15",
			"name": "Veronica Schuppe",
			"state": "Indiana",
			"createAt": "2021-05-22T00:14:24.224Z"
		},
		{
			"id": "16",
			"name": "Elaine Pfeffer",
			"state": "Iowa",
			"createAt": "2021-05-22T05:55:23.324Z"
		},
		{
			"id": "17",
			"name": "Lamar Gislason",
			"state": "Oregon",
			"createAt": "2021-05-22T02:45:07.015Z"
		},
		{
			"id": "18",
			"name": "Louise Abernathy",
			"state": "Florida",
			"createAt": "2021-05-22T12:54:13.607Z"
		},
		{
			"id": "19",
			"name": "Mr. Bertha Skiles",
			"state": "Vermont",
			"createAt": "2021-05-21T20:08:38.389Z"
		},
		{
			"id": "20",
			"name": "Jennie Terry",
			"state": "New York",
			"createAt": "2021-05-22T14:08:30.264Z"
		}
	]
}
